thrift/TMultiplexedProcessor.py
thrift/TRecursive.py
thrift/TSCons.py
thrift/TSerialization.py
thrift/TTornado.py
thrift/Thrift.py
thrift/__init__.py
thrift/compat.py
thrift/__pycache__/TMultiplexedProcessor.cpython-36.opt-1.pyc
thrift/__pycache__/TRecursive.cpython-36.opt-1.pyc
thrift/__pycache__/TSCons.cpython-36.opt-1.pyc
thrift/__pycache__/TSerialization.cpython-36.opt-1.pyc
thrift/__pycache__/TTornado.cpython-36.opt-1.pyc
thrift/__pycache__/Thrift.cpython-36.opt-1.pyc
thrift/__pycache__/__init__.cpython-36.opt-1.pyc
thrift/__pycache__/compat.cpython-36.opt-1.pyc
thrift/protocol/TBase.py
thrift/protocol/TBinaryProtocol.py
thrift/protocol/TCompactProtocol.py
thrift/protocol/THeaderProtocol.py
thrift/protocol/TJSONProtocol.py
thrift/protocol/TMultiplexedProtocol.py
thrift/protocol/TProtocol.py
thrift/protocol/TProtocolDecorator.py
thrift/protocol/__init__.py
thrift/protocol/fastbinary.cpython-36m-darwin.so
thrift/protocol/__pycache__/TBase.cpython-36.opt-1.pyc
thrift/protocol/__pycache__/TBinaryProtocol.cpython-36.opt-1.pyc
thrift/protocol/__pycache__/TCompactProtocol.cpython-36.opt-1.pyc
thrift/protocol/__pycache__/THeaderProtocol.cpython-36.opt-1.pyc
thrift/protocol/__pycache__/TJSONProtocol.cpython-36.opt-1.pyc
thrift/protocol/__pycache__/TMultiplexedProtocol.cpython-36.opt-1.pyc
thrift/protocol/__pycache__/TProtocol.cpython-36.opt-1.pyc
thrift/protocol/__pycache__/TProtocolDecorator.cpython-36.opt-1.pyc
thrift/protocol/__pycache__/__init__.cpython-36.opt-1.pyc
thrift/server/THttpServer.py
thrift/server/TNonblockingServer.py
thrift/server/TProcessPoolServer.py
thrift/server/TServer.py
thrift/server/__init__.py
thrift/server/__pycache__/THttpServer.cpython-36.opt-1.pyc
thrift/server/__pycache__/TNonblockingServer.cpython-36.opt-1.pyc
thrift/server/__pycache__/TProcessPoolServer.cpython-36.opt-1.pyc
thrift/server/__pycache__/TServer.cpython-36.opt-1.pyc
thrift/server/__pycache__/__init__.cpython-36.opt-1.pyc
thrift_adv-1.0.0.dev0.dist-info/METADATA
thrift_adv-1.0.0.dev0.dist-info/RECORD
thrift_adv-1.0.0.dev0.dist-info/WHEEL
thrift_adv-1.0.0.dev0.dist-info/top_level.txt
